[
    {
        "date": "2025-04-22",
        "time": "16:02:39",
        "bet_amount": 10.0,
        "multiplier": 1.92,
        "decided_multiplier": {
            "multiplier_for_box_one": 1.8,
            "multiplier_for_box_two": 1.0
        },
        "result_one": "draw",
        "result_two": "draw",
        "initial_balance": 6509.59,
        "current_balance": 6509.59,
        "multiplier_category": "B",
        "decided_multiplier_one_category": "B",
        "decided_multiplier_two_category": "B"
    },
    {
        "date": "2025-04-22",
        "time": "16:03:00",
        "bet_amount": 10.0,
        "multiplier": 2.88,
        "decided_multiplier": {
            "multiplier_for_box_one": 1.8,
            "multiplier_for_box_two": 1.0
        },
        "result_one": "win",
        "result_two": "draw",
        "initial_balance": 6509.59,
        "current_balance": 6517.89,
        "multiplier_category": "P",
        "decided_multiplier_one_category": "B",
        "decided_multiplier_two_category": "B"
    },
    {
        "date": "2025-04-22",
        "time": "16:03:23",
        "bet_amount": 10.0,
        "multiplier": 1.67,
        "decided_multiplier": {
            "multiplier_for_box_one": 1.8,
            "multiplier_for_box_two": 1.0
        },
        "result_one": "draw",
        "result_two": "draw",
        "initial_balance": 6509.59,
        "current_balance": 6517.89,
        "multiplier_category": "B",
        "decided_multiplier_one_category": "B",
        "decided_multiplier_two_category": "B"
    },
    {
        "date": "2025-04-22",
        "time": "16:03:41",
        "bet_amount": 10.0,
        "multiplier": 13.0,
        "decided_multiplier": {
            "multiplier_for_box_one": 1.8,
            "multiplier_for_box_two": 1.0
        },
        "result_one": "win",
        "result_two": "draw",
        "initial_balance": 6509.59,
        "current_balance": 6525.99,
        "multiplier_category": "Pk",
        "decided_multiplier_one_category": "B",
        "decided_multiplier_two_category": "B"
    },
    {
        "date": "2025-04-22",
        "time": "16:04:24",
        "bet_amount": 10.0,
        "multiplier": 1.99,
        "decided_multiplier": {
            "multiplier_for_box_one": 1.8,
            "multiplier_for_box_two": 1.0
        },
        "result_one": "draw",
        "result_two": "draw",
        "initial_balance": 6509.59,
        "current_balance": 6525.99,
        "multiplier_category": "B",
        "decided_multiplier_one_category": "B",
        "decided_multiplier_two_category": "B"
    },
    {
        "date": "2025-04-22",
        "time": "16:04:45",
        "bet_amount": 10.0,
        "multiplier": 1.17,
        "decided_multiplier": {
            "multiplier_for_box_one": 1.8,
            "multiplier_for_box_two": 1.0
        },
        "result_one": "loss",
        "result_two": "draw",
        "initial_balance": 6509.59,
        "current_balance": 6515.99,
        "multiplier_category": "B",
        "decided_multiplier_one_category": "B",
        "decided_multiplier_two_category": "B"
    }
]